cli/__init__.py
cli/add.py
cli/build.py
cli/checksum.py
cli/conescenes.py
conescenes-1.0.0.dist-info/LICENSE
conescenes-1.0.0.dist-info/METADATA
conescenes-1.0.0.dist-info/WHEEL
conescenes-1.0.0.dist-info/entry_points.txt
conescenes-1.0.0.dist-info/top_level.txt
conescenes-1.0.0.dist-info/RECORD
