Metadata-Version: 2.1
Name: conescenes
Version: 1.0.0
License-File: LICENSE
Requires-Dist: click
Requires-Dist: termcolor
Requires-Dist: datetime
Requires-Dist: zipfile
Requires-Dist: tkinter
Requires-Dist: numpy
Requires-Dist: json
